arkivist/__init__.py
arkivist/arkivist - Copy.py
arkivist/arkivist.py
arkivist/version.py
arkivist-1.3.4.dist-info/LICENSE
arkivist-1.3.4.dist-info/METADATA
arkivist-1.3.4.dist-info/WHEEL
arkivist-1.3.4.dist-info/top_level.txt
arkivist-1.3.4.dist-info/RECORD
