Metadata-Version: 2.1
Name: arkivist
Version: 1.3.4
Summary: Arkivist, a Python Dictionary wrapper for JSON files.
Home-page: https://github.com/rmaniego/arkivist
Download-URL: https://github.com/rmaniego/arkivist/archive/v1.0.tar.gz
Author: Rodney Maniego Jr.
Author-email: rodney.maniegojr@gmail.com
License: MIT
Keywords: dictionary,json,storage
Classifier: Development Status :: 5 - Production/Stable
Classifier: Intended Audience :: Developers
Classifier: Topic :: Software Development :: Build Tools
Classifier: License :: OSI Approved :: MIT License
Classifier: Programming Language :: Python :: 3
Requires-Python: >=3.9
License-File: LICENSE
Requires-Dist: cryptography
Requires-Dist: requests
